jpmodel/__init__.py
jpmodel/mol_preproc_v1.py
jpmodel/v1.py
jpmodel-0.0.4.dist-info/METADATA
jpmodel-0.0.4.dist-info/WHEEL
jpmodel-0.0.4.dist-info/top_level.txt
jpmodel-0.0.4.dist-info/RECORD
